Metadata-Version: 1.0
Name: ansible-coverage-callback
Version: 1.0.1
Summary: Simple Ansible Coverage callback
Home-page: https://github.com/leominov/ansible-coverage-callback
Author: Lev Aminov
Author-email: l.aminov@tinkoff.ru
License: MIT
Platform: UNKNOWN
